pyvote/__init__.py
pyvote_api-0.0.1.dist-info/LICENSE
pyvote_api-0.0.1.dist-info/METADATA
pyvote_api-0.0.1.dist-info/WHEEL
pyvote_api-0.0.1.dist-info/top_level.txt
pyvote_api-0.0.1.dist-info/RECORD
