Metadata-Version: 2.1
Name: pyvote-api
Version: 0.0.1
Summary: Simple voting API
Home-page: https://github.com/c-base/pyvote
Author: baccenfutter
Author-email: baccenfutter@c-base.org
License: UNKNOWN
Platform: UNKNOWN
Classifier: Programming Language :: Python :: 3
Classifier: License :: OSI Approved :: MIT License
Classifier: Operating System :: OS Independent
Requires-Python: >=3.6
